Loggy/Loggy.py
Loggy/__init__.py
Loggy/module/LogLevelEnum.py
Loggy/module/LoggyTheme.py
Loggy/module/__init__.py
Loggy/module/termcolor.py
Loggy/theme/ClassicTheme.py
Loggy/theme/__init__.py
LoggyLogger-1.0.1.dist-info/METADATA
LoggyLogger-1.0.1.dist-info/WHEEL
LoggyLogger-1.0.1.dist-info/top_level.txt
LoggyLogger-1.0.1.dist-info/RECORD
