Metadata-Version: 2.1
Name: LoggyLogger
Version: 1.0.1
Summary: Convenient, friendly and clean logger for Python
Home-page: https://github.com/eric12345566/loggy
Author: Eric Shih
Author-email: eric12345566@gmail.com
License: UNKNOWN
Platform: UNKNOWN
Classifier: Programming Language :: Python :: 3
Classifier: License :: OSI Approved :: MIT License
Classifier: Operating System :: OS Independent
Classifier: Topic :: System :: Logging
Requires-Python: >=3
